Workbook

Sheet README
A1: analysis.xlsx - every number in memo.md traces to a formula here.
A2: Blue = typed input (copied from the CSVs). Black = formula. Yellow = assumption you can change.
A3: INVENTED data: Traffic sheet (given by TechAbout). REAL data: Articles sheet (scraped headlines).
A4: Sheets: Traffic -> Step -> Underlying -> Nov -> Guides ; Articles -> Windows ; Checks.
A5: Scrape date (Articles!J1) is 2026-10-03, the day the pages were opened. Relative dates like '5 days ago' are counted back from it.

Sheet Traffic
A1: month | B1: AI | C1: Markets | D1: Crypto | E1: Breakthroughs | F1: Policy | G1: Guides | H1: newsletter_signups | I1: post_swap (1=after 1 Feb) | J1: Total sessions | K1: Total ex-Guides | L1: Sessions per signup | M1: Total MoM %
A2: 2025-09 | B2: 18400 | C2: 12200 | D2: 9800 | E2: 7600 | F2: 5400 | G2: 4100 | H2: 820 | I2: 0 | J2: =SUM(B2:G2) -> 57500 | K2: =SUM(B2:F2) -> 53400 | L2: =J2/H2 -> 70.121951
A3: 2025-10 | B3: 19100 | C3: 12500 | D3: 10100 | E3: 7800 | F3: 5500 | G3: 4000 | H3: 840 | I3: 0 | J3: =SUM(B3:G3) -> 59000 | K3: =SUM(B3:F3) -> 55000 | L3: =J3/H3 -> 70.238095 | M3: =J3/J2-1 -> 0.026086957
A4: 2025-11 | B4: 19800 | C4: 12800 | D4: 24800 | E4: 8100 | F4: 5600 | G4: 3900 | H4: 860 | I4: 0 | J4: =SUM(B4:G4) -> 75000 | K4: =SUM(B4:F4) -> 71100 | L4: =J4/H4 -> 87.209302 | M4: =J4/J3-1 -> 0.27118644
A5: 2025-12 | B5: 20500 | C5: 13100 | D5: 11000 | E5: 8300 | F5: 5700 | G5: 3800 | H5: 890 | I5: 0 | J5: =SUM(B5:G5) -> 62400 | K5: =SUM(B5:F5) -> 58600 | L5: =J5/H5 -> 70.11236 | M5: =J5/J4-1 -> -0.168
A6: 2026-01 | B6: 21200 | C6: 13400 | D6: 11400 | E6: 8500 | F6: 5800 | G6: 3700 | H6: 920 | I6: 0 | J6: =SUM(B6:G6) -> 64000 | K6: =SUM(B6:F6) -> 60300 | L6: =J6/H6 -> 69.565217 | M6: =J6/J5-1 -> 0.025641026
A7: 2026-02 | B7: 31610 | C7: 19865 | D7: 16820 | E7: 12615 | F7: 8555 | G7: 5220 | H7: 950 | I7: 1 | J7: =SUM(B7:G7) -> 94685 | K7: =SUM(B7:F7) -> 89465 | L7: =J7/H7 -> 99.668421 | M7: =J7/J6-1 -> 0.47945312
A8: 2026-03 | B8: 32480 | C8: 20300 | D8: 17255 | E8: 12905 | F8: 8700 | G8: 4930 | H8: 980 | I8: 1 | J8: =SUM(B8:G8) -> 96570 | K8: =SUM(B8:F8) -> 91640 | L8: =J8/H8 -> 98.540816 | M8: =J8/J7-1 -> 0.019908116
A9: 2026-04 | B9: 33350 | C9: 20735 | D9: 17545 | E9: 13195 | F9: 8845 | G9: 2175 | H9: 1010 | I9: 1 | J9: =SUM(B9:G9) -> 95845 | K9: =SUM(B9:F9) -> 93670 | L9: =J9/H9 -> 94.89604 | M9: =J9/J8-1 -> -0.0075075075
A10: 2026-05 | B10: 34220 | C10: 21170 | D10: 17980 | E10: 13485 | F10: 8990 | G10: 1595 | H10: 1040 | I10: 1 | J10: =SUM(B10:G10) -> 97440 | K10: =SUM(B10:F10) -> 95845 | L10: =J10/H10 -> 93.692308 | M10: =J10/J9-1 -> 0.016641452
A11: 2026-06 | B11: 35090 | C11: 21605 | D11: 18270 | E11: 13775 | F11: 9135 | G11: 1160 | H11: 1070 | I11: 1 | J11: =SUM(B11:G11) -> 99035 | K11: =SUM(B11:F11) -> 97875 | L11: =J11/H11 -> 92.556075 | M11: =J11/J10-1 -> 0.016369048
A12: 2026-07 | B12: 35960 | C12: 22040 | D12: 18705 | E12: 14065 | F12: 9280 | G12: 870 | H12: 1100 | I12: 1 | J12: =SUM(B12:G12) -> 100920 | K12: =SUM(B12:F12) -> 100050 | L12: =J12/H12 -> 91.745455 | M12: =J12/J11-1 -> 0.019033675
A13: 2026-08 | B13: 36830 | C13: 22475 | D13: 18995 | E13: 14355 | F13: 9425 | G13: 725 | H13: 1140 | I13: 1 | J13: =SUM(B13:G13) -> 102805 | K13: =SUM(B13:F13) -> 102080 | L13: =J13/H13 -> 90.179825 | M13: =J13/J12-1 -> 0.018678161
A15: Source: traffic_table.csv (INVENTED by TechAbout). Rows 2-13 = Sep-25..Aug-26. No month is a year apart, so true YoY cannot be computed.
A16: Typical MoM (excl. Nov, Dec, Feb): | D16: =(M3+M6+M8+M9+M10+M11+M12+M13)/8 -> 0.016856366
A17: Feb step (total): | D17: =M7 -> 0.47945312
A18: Feb step / typical month: | D18: =D17/D16 -> 28.443446

Sheet Step
A1: Section | B1: Sep-25 | C1: Jan-26 | D1: Feb-26 | E1: Pre-swap monthly gain =(Jan-Sep)/4 | F1: Expected Feb with no swap | G1: Step k = Feb / expected | H1: Raw Feb/Jan (upper bound, zero growth)
A2: AI | B2: =Traffic!B2 -> 18400 | C2: =Traffic!B6 -> 21200 | D2: =Traffic!B7 -> 31610 | E2: =(C2-B2)/4 -> 700 | F2: =C2+E2 -> 21900 | G2: =D2/F2 -> 1.443379 | H2: =D2/C2 -> 1.4910377
A3: Markets | B3: =Traffic!C2 -> 12200 | C3: =Traffic!C6 -> 13400 | D3: =Traffic!C7 -> 19865 | E3: =(C3-B3)/4 -> 300 | F3: =C3+E3 -> 13700 | G3: =D3/F3 -> 1.45 | H3: =D3/C3 -> 1.4824627
A4: Crypto | B4: =Traffic!D2 -> 9800 | C4: =Traffic!D6 -> 11400 | D4: =Traffic!D7 -> 16820 | E4: =(C4-B4)/4 -> 400 | F4: =C4+E4 -> 11800 | G4: =D4/F4 -> 1.4254237 | H4: =D4/C4 -> 1.4754386
A5: Breakthroughs | B5: =Traffic!E2 -> 7600 | C5: =Traffic!E6 -> 8500 | D5: =Traffic!E7 -> 12615 | E5: =(C5-B5)/4 -> 225 | F5: =C5+E5 -> 8725 | G5: =D5/F5 -> 1.4458453 | H5: =D5/C5 -> 1.4841176
A6: Policy | B6: =Traffic!F2 -> 5400 | C6: =Traffic!F6 -> 5800 | D6: =Traffic!F7 -> 8555 | E6: =(C6-B6)/4 -> 100 | F6: =C6+E6 -> 5900 | G6: =D6/F6 -> 1.45 | H6: =D6/C6 -> 1.475
A7: Guides | B7: =Traffic!G2 -> 4100 | C7: =Traffic!G6 -> 3700 | D7: =Traffic!G7 -> 5220 | E7: =(C7-B7)/4 -> -100 | F7: =C7+E7 -> 3600 | G7: =D7/F7 -> 1.45 | H7: =D7/C7 -> 1.4108108
A9: Total | B9: =SUM(B2:B7) -> 57500 | C9: =SUM(C2:C7) -> 64000 | D9: =SUM(D2:D7) -> 94685 | E9: =SUM(E2:E7) -> 1625 | F9: =SUM(F2:F7) -> 65625 | G9: =D9/F9 -> 1.442819 | H9: =D9/C9 -> 1.4794531
A11: k LOW (smallest section) | B11: =MIN(G2:G7) -> 1.4254237
A12: k CENTRAL (total Feb / total expected) | B12: =G9 -> 1.442819
A13: k HIGH (total Feb / Jan, assumes zero real growth) | B13: =H9 -> 1.4794531
A15: Reading: six sections with different trends (+3% a month to -2.6% a month) all step by 1.43 to 1.45 in the same month. Real audience events do not do that. Crypto is lowest because its Jan level was already rising faster (400 a month).

Sheet Underlying
A1: month | B1: Reported total | C1: post_swap | D1: Adjusted total (central k) | E1: Adjusted ex-Guides (central k) | F1: Signups | G1: Index reported | H1: Index adjusted | I1: Index signups
A2: =Traffic!A2 -> 2025-09 | B2: =Traffic!J2 -> 57500 | C2: =Traffic!I2 -> 0 | D2: =B2/IF(C2=1,Step!$B$12,1) -> 57500 | E2: =Traffic!K2/IF(C2=1,Step!$B$12,1) -> 53400 | F2: =Traffic!H2 -> 820 | G2: =B2/$B$2*100 -> 100 | H2: =D2/$D$2*100 -> 100 | I2: =F2/$F$2*100 -> 100
A3: =Traffic!A3 -> 2025-10 | B3: =Traffic!J3 -> 59000 | C3: =Traffic!I3 -> 0 | D3: =B3/IF(C3=1,Step!$B$12,1) -> 59000 | E3: =Traffic!K3/IF(C3=1,Step!$B$12,1) -> 55000 | F3: =Traffic!H3 -> 840 | G3: =B3/$B$2*100 -> 102.6087 | H3: =D3/$D$2*100 -> 102.6087 | I3: =F3/$F$2*100 -> 102.43902
A4: =Traffic!A4 -> 2025-11 | B4: =Traffic!J4 -> 75000 | C4: =Traffic!I4 -> 0 | D4: =B4/IF(C4=1,Step!$B$12,1) -> 75000 | E4: =Traffic!K4/IF(C4=1,Step!$B$12,1) -> 71100 | F4: =Traffic!H4 -> 860 | G4: =B4/$B$2*100 -> 130.43478 | H4: =D4/$D$2*100 -> 130.43478 | I4: =F4/$F$2*100 -> 104.87805
A5: =Traffic!A5 -> 2025-12 | B5: =Traffic!J5 -> 62400 | C5: =Traffic!I5 -> 0 | D5: =B5/IF(C5=1,Step!$B$12,1) -> 62400 | E5: =Traffic!K5/IF(C5=1,Step!$B$12,1) -> 58600 | F5: =Traffic!H5 -> 890 | G5: =B5/$B$2*100 -> 108.52174 | H5: =D5/$D$2*100 -> 108.52174 | I5: =F5/$F$2*100 -> 108.53659
A6: =Traffic!A6 -> 2026-01 | B6: =Traffic!J6 -> 64000 | C6: =Traffic!I6 -> 0 | D6: =B6/IF(C6=1,Step!$B$12,1) -> 64000 | E6: =Traffic!K6/IF(C6=1,Step!$B$12,1) -> 60300 | F6: =Traffic!H6 -> 920 | G6: =B6/$B$2*100 -> 111.30435 | H6: =D6/$D$2*100 -> 111.30435 | I6: =F6/$F$2*100 -> 112.19512
A7: =Traffic!A7 -> 2026-02 | B7: =Traffic!J7 -> 94685 | C7: =Traffic!I7 -> 1 | D7: =B7/IF(C7=1,Step!$B$12,1) -> 65625 | E7: =Traffic!K7/IF(C7=1,Step!$B$12,1) -> 62007.083 | F7: =Traffic!H7 -> 950 | G7: =B7/$B$2*100 -> 164.66957 | H7: =D7/$D$2*100 -> 114.13043 | I7: =F7/$F$2*100 -> 115.85366
A8: =Traffic!A8 -> 2026-03 | B8: =Traffic!J8 -> 96570 | C8: =Traffic!I8 -> 1 | D8: =B8/IF(C8=1,Step!$B$12,1) -> 66931.47 | E8: =Traffic!K8/IF(C8=1,Step!$B$12,1) -> 63514.548 | F8: =Traffic!H8 -> 980 | G8: =B8/$B$2*100 -> 167.94783 | H8: =D8/$D$2*100 -> 116.40256 | I8: =F8/$F$2*100 -> 119.5122
A9: =Traffic!A9 -> 2026-04 | B9: =Traffic!J9 -> 95845 | C9: =Traffic!I9 -> 1 | D9: =B9/IF(C9=1,Step!$B$12,1) -> 66428.982 | E9: =Traffic!K9/IF(C9=1,Step!$B$12,1) -> 64921.516 | F9: =Traffic!H9 -> 1010 | G9: =B9/$B$2*100 -> 166.68696 | H9: =D9/$D$2*100 -> 115.52866 | I9: =F9/$F$2*100 -> 123.17073
A10: =Traffic!A10 -> 2026-05 | B10: =Traffic!J10 -> 97440 | C10: =Traffic!I10 -> 1 | D10: =B10/IF(C10=1,Step!$B$12,1) -> 67534.456 | E10: =Traffic!K10/IF(C10=1,Step!$B$12,1) -> 66428.982 | F10: =Traffic!H10 -> 1040 | G10: =B10/$B$2*100 -> 169.46087 | H10: =D10/$D$2*100 -> 117.45123 | I10: =F10/$F$2*100 -> 126.82927
A11: =Traffic!A11 -> 2026-06 | B11: =Traffic!J11 -> 99035 | C11: =Traffic!I11 -> 1 | D11: =B11/IF(C11=1,Step!$B$12,1) -> 68639.931 | E11: =Traffic!K11/IF(C11=1,Step!$B$12,1) -> 67835.949 | F11: =Traffic!H11 -> 1070 | G11: =B11/$B$2*100 -> 172.23478 | H11: =D11/$D$2*100 -> 119.37379 | I11: =F11/$F$2*100 -> 130.4878
A12: =Traffic!A12 -> 2026-07 | B12: =Traffic!J12 -> 100920 | C12: =Traffic!I12 -> 1 | D12: =B12/IF(C12=1,Step!$B$12,1) -> 69946.401 | E12: =Traffic!K12/IF(C12=1,Step!$B$12,1) -> 69343.415 | F12: =Traffic!H12 -> 1100 | G12: =B12/$B$2*100 -> 175.51304 | H12: =D12/$D$2*100 -> 121.64592 | I12: =F12/$F$2*100 -> 134.14634
A13: =Traffic!A13 -> 2026-08 | B13: =Traffic!J13 -> 102805 | C13: =Traffic!I13 -> 1 | D13: =B13/IF(C13=1,Step!$B$12,1) -> 71252.871 | E13: =Traffic!K13/IF(C13=1,Step!$B$12,1) -> 70750.383 | F13: =Traffic!H13 -> 1140 | G13: =B13/$B$2*100 -> 178.7913 | H13: =D13/$D$2*100 -> 123.91804 | I13: =F13/$F$2*100 -> 139.02439
A15: Aug-26 vs Sep-25, REPORTED (11 months apart, not YoY) | B15: =B13/B2-1 -> 0.78791304
A16: Aug-26 vs Sep-25, UNDERLYING, central k | B16: =D13/D2-1 -> 0.23918037
A17: low-growth end (k HIGH) | B17: =(B13/Step!B13)/D2-1 -> 0.20849591
A18: high-growth end (k LOW) | B18: =(B13/Step!B11)/D2-1 -> 0.25430285
A19: Underlying, annualised equivalent =(1+x)^(12/11)-1 | B19: =(1+B16)^(12/11)-1 -> 0.2635758
A20: Underlying ex-Guides, central k | B20: =E13/E2-1 -> 0.32491354
A21: Signups Aug-26 vs Sep-25 | B21: =F13/F2-1 -> 0.3902439
A22: Signups annualised equivalent | B22: =(1+B21)^(12/11)-1 -> 0.43251531
A23: Share of reported Aug growth that is measurement | B23: =1-B16/B15 -> 0.69643811
A25: Method: divide every month from Feb by k (flag in col C). Assumes the swap multiplied ALL sections by the same factor and did not change signups. Both are assumptions - see memo.

Sheet Nov
A1: Crypto Oct-25 | B1: =Traffic!D3 -> 10100
A2: Crypto Nov-25 | B2: =Traffic!D4 -> 24800
A3: Crypto Dec-25 | B3: =Traffic!D5 -> 11000
A4: Neighbour mean (Oct, Dec) | B4: =(B1+B3)/2 -> 10550
A5: Nov excess sessions | B5: =B2-B4 -> 14250
A6: Excess as % of Crypto Nov | B6: =B5/B2 -> 0.57459677
A7: Site total Nov | B7: =Traffic!J4 -> 75000
A8: Excess as % of site Nov | B8: =B5/B7 -> 0.19
A9: Dec-25 vs neighbour trend: Dec - Oct | B9: =B3-B1 -> 900
A10: Signups Nov | B10: =Traffic!H4 -> 860
A11: Signups neighbour mean (Oct, Dec) | B11: =(Traffic!H3+Traffic!H5)/2 -> 865
A12: Signup excess in Nov | B12: =B10-B11 -> -5
A13: Excess sessions per excess signup | B13: =IF(B12<=0,"none: signups did not rise",B5/B12) -> none: signups did not rise
A15: Read: one month, back on trend in December, almost zero signups from about 14,000 extra sessions. Real readers, but a one-off and worth nothing to subscriber-priced slots.

Sheet Articles
A1: Articles: REAL data, 120 rows from the six TECHi section pages | I1: Scrape date: | J1: 46298
A3: url | B3: section | C3: headline | D3: author | E3: date_shown | F3: headline_word_count | G3: format | H3: names_a_company | I3: contains_a_number | J3: date_parsed | K3: month_key | L3: ticker_type (keyword rule)
A4: https://www.techi.com/gumloop-ai-review/ | B4: AI | C4: Gumloop AI review: powerful agents, complicated economics | D4: Jazib Zaman | E4: 10 hours ago | F4: 7 | G4: review | H4: 1 | I4: 0 | J4: =IF(ISNUMBER(SEARCH("hour",E4)),INT($J$1-VALUE(LEFT(E4,FIND(" ",E4)-1))/24),IF(ISNUMBER(SEARCH("day",E4)),$J$1-VALUE(LEFT(E4,FIND(" ",E4)-1)),DATE(2000+VALUE(RIGHT(E4,2)),MATCH(MID(E4,FIND("-",E4)+1,3),{"Jan","Feb","Mar","Apr","May","Jun","Jul","Aug","Sep","Oct","Nov","Dec"},0),VALUE(LEFT(E4,FIND("-",E4)-1))))) -> 46297 | K4: =YEAR(J4)*100+MONTH(J4) -> 202610 | L4: =IF(OR(ISNUMBER(SEARCH("stock",C4)),ISNUMBER(SEARCH("forecast",C4)),ISNUMBER(SEARCH("earnings",C4)),ISNUMBER(SEARCH("ipo ",C4&" ")),ISNUMBER(SEARCH("ipo,",C4)),ISNUMBER(SEARCH("lockup",C4)),ISNUMBER(SEARCH("price",C4)),ISNUMBER(SEARCH("mstr",C4)),ISNUMBER(SEARCH("tsm",C4)),ISNUMBER(SEARCH("nvda",C4)),ISNUMBER(SEARCH(" vs ",C4))),1,0) -> 0
A5: https://www.techi.com/palantir-stock-forecast-october-2026-estimate-gap/ | B5: AI | C5: Palantir Stock Forecast for October 2026: The Estimate Gap | D5: Fatimah Misbah Hussain | E5: 2 days ago | F5: 9 | G5: analysis | H5: 1 | I5: 1 | J5: =IF(ISNUMBER(SEARCH("hour",E5)),INT($J$1-VALUE(LEFT(E5,FIND(" ",E5)-1))/24),IF(ISNUMBER(SEARCH("day",E5)),$J$1-VALUE(LEFT(E5,FIND(" ",E5)-1)),DATE(2000+VALUE(RIGHT(E5,2)),MATCH(MID(E5,FIND("-",E5)+1,3),{"Jan","Feb","Mar","Apr","May","Jun","Jul","Aug","Sep","Oct","Nov","Dec"},0),VALUE(LEFT(E5,FIND("-",E5)-1))))) -> 46296 | K5: =YEAR(J5)*100+MONTH(J5) -> 202610 | L5: =IF(OR(ISNUMBER(SEARCH("stock",C5)),ISNUMBER(SEARCH("forecast",C5)),ISNUMBER(SEARCH("earnings",C5)),ISNUMBER(SEARCH("ipo ",C5&" ")),ISNUMBER(SEARCH("ipo,",C5)),ISNUMBER(SEARCH("lockup",C5)),ISNUMBER(SEARCH("price",C5)),ISNUMBER(SEARCH("mstr",C5)),ISNUMBER(SEARCH("tsm",C5)),ISNUMBER(SEARCH("nvda",C5)),ISNUMBER(SEARCH(" vs ",C5))),1,0) -> 1
A6: https://www.techi.com/nvidia-vs-micron-buyback-hbm-earnings-2026/ | B6: AI | C6: Nvidia vs Micron Ahead of Earnings: Buyback Capacity or HBM Growth? | D6: Fatimah Misbah Hussain | E6: 3 days ago | F6: 11 | G6: analysis | H6: 1 | I6: 0 | J6: =IF(ISNUMBER(SEARCH("hour",E6)),INT($J$1-VALUE(LEFT(E6,FIND(" ",E6)-1))/24),IF(ISNUMBER(SEARCH("day",E6)),$J$1-VALUE(LEFT(E6,FIND(" ",E6)-1)),DATE(2000+VALUE(RIGHT(E6,2)),MATCH(MID(E6,FIND("-",E6)+1,3),{"Jan","Feb","Mar","Apr","May","Jun","Jul","Aug","Sep","Oct","Nov","Dec"},0),VALUE(LEFT(E6,FIND("-",E6)-1))))) -> 46295 | K6: =YEAR(J6)*100+MONTH(J6) -> 202609 | L6: =IF(OR(ISNUMBER(SEARCH("stock",C6)),ISNUMBER(SEARCH("forecast",C6)),ISNUMBER(SEARCH("earnings",C6)),ISNUMBER(SEARCH("ipo ",C6&" ")),ISNUMBER(SEARCH("ipo,",C6)),ISNUMBER(SEARCH("lockup",C6)),ISNUMBER(SEARCH("price",C6)),ISNUMBER(SEARCH("mstr",C6)),ISNUMBER(SEARCH("tsm",C6)),ISNUMBER(SEARCH("nvda",C6)),ISNUMBER(SEARCH(" vs ",C6))),1,0) -> 1
A7: https://www.techi.com/verusd-stablecoin-launch-ai-agent-commitments/ | B7: AI | C7: verUSD Stablecoin Launch: What Verona’s $100M AI-Agent Commitments Mean | D7: Zoha Imdad Ali | E7: 3 days ago | F7: 9 | G7: news | H7: 1 | I7: 1 | J7: =IF(ISNUMBER(SEARCH("hour",E7)),INT($J$1-VALUE(LEFT(E7,FIND(" ",E7)-1))/24),IF(ISNUMBER(SEARCH("day",E7)),$J$1-VALUE(LEFT(E7,FIND(" ",E7)-1)),DATE(2000+VALUE(RIGHT(E7,2)),MATCH(MID(E7,FIND("-",E7)+1,3),{"Jan","Feb","Mar","Apr","May","Jun","Jul","Aug","Sep","Oct","Nov","Dec"},0),VALUE(LEFT(E7,FIND("-",E7)-1))))) -> 46295 | K7: =YEAR(J7)*100+MONTH(J7) -> 202609 | L7: =IF(OR(ISNUMBER(SEARCH("stock",C7)),ISNUMBER(SEARCH("forecast",C7)),ISNUMBER(SEARCH("earnings",C7)),ISNUMBER(SEARCH("ipo ",C7&" ")),ISNUMBER(SEARCH("ipo,",C7)),ISNUMBER(SEARCH("lockup",C7)),ISNUMBER(SEARCH("price",C7)),ISNUMBER(SEARCH("mstr",C7)),ISNUMBER(SEARCH("tsm",C7)),ISNUMBER(SEARCH("nvda",C7)),ISNUMBER(SEARCH(" vs ",C7))),1,0) -> 0
A8: https://www.techi.com/dc-circuit-pentagon-anthropic-supply-chain-ruling/ | B8: AI | C8: D.C. Circuit upholds Pentagon’s Anthropic supply-chain exclusion | D8: Saba Javed | E8: 4 days ago | F8: 7 | G8: news | H8: 1 | I8: 0 | J8: =IF(ISNUMBER(SEARCH("hour",E8)),INT($J$1-VALUE(LEFT(E8,FIND(" ",E8)-1))/24),IF(ISNUMBER(SEARCH("day",E8)),$J$1-VALUE(LEFT(E8,FIND(" ",E8)-1)),DATE(2000+VALUE(RIGHT(E8,2)),MATCH(MID(E8,FIND("-",E8)+1,3),{"Jan","Feb","Mar","Apr","May","Jun","Jul","Aug","Sep","Oct","Nov","Dec"},0),VALUE(LEFT(E8,FIND("-",E8)-1))))) -> 46294 | K8: =YEAR(J8)*100+MONTH(J8) -> 202609 | L8: =IF(OR(ISNUMBER(SEARCH("stock",C8)),ISNUMBER(SEARCH("forecast",C8)),ISNUMBER(SEARCH("earnings",C8)),ISNUMBER(SEARCH("ipo ",C8&" ")),ISNUMBER(SEARCH("ipo,",C8)),ISNUMBER(SEARCH("lockup",C8)),ISNUMBER(SEARCH("price",C8)),ISNUMBER(SEARCH("mstr",C8)),ISNUMBER(SEARCH("tsm",C8)),ISNUMBER(SEARCH("nvda",C8)),ISNUMBER(SEARCH(" vs ",C8))),1,0) -> 0
A9: https://www.techi.com/nvidia-vs-tesla-stock-ai-trade-today/ | B9: AI | C9: Nvidia vs Tesla Stock: Why NVDA Wins the AI Trade Today | D9: Omer Sheikh | E9: 4 days ago | F9: 11 | G9: analysis | H9: 1 | I9: 0 | J9: =IF(ISNUMBER(SEARCH("hour",E9)),INT($J$1-VALUE(LEFT(E9,FIND(" ",E9)-1))/24),IF(ISNUMBER(SEARCH("day",E9)),$J$1-VALUE(LEFT(E9,FIND(" ",E9)-1)),DATE(2000+VALUE(RIGHT(E9,2)),MATCH(MID(E9,FIND("-",E9)+1,3),{"Jan","Feb","Mar","Apr","May","Jun","Jul","Aug","Sep","Oct","Nov","Dec"},0),VALUE(LEFT(E9,FIND("-",E9)-1))))) -> 46294 | K9: =YEAR(J9)*100+MONTH(J9) -> 202609 | L9: =IF(OR(ISNUMBER(SEARCH("stock",C9)),ISNUMBER(SEARCH("forecast",C9)),ISNUMBER(SEARCH("earnings",C9)),ISNUMBER(SEARCH("ipo ",C9&" ")),ISNUMBER(SEARCH("ipo,",C9)),ISNUMBER(SEARCH("lockup",C9)),ISNUMBER(SEARCH("price",C9)),ISNUMBER(SEARCH("mstr",C9)),ISNUMBER(SEARCH("tsm",C9)),ISNUMBER(SEARCH("nvda",C9)),ISNUMBER(SEARCH(" vs ",C9))),1,0) -> 1
A10: https://www.techi.com/openai-pauses-ai-model-training-agent-dns-sandbox/ | B10: AI | C10: OpenAI Pauses AI Model Work After Agent Escapes Its Sandbox | D10: Saba Javed | E10: 5 days ago | F10: 10 | G10: news | H10: 1 | I10: 0 | J10: =IF(ISNUMBER(SEARCH("hour",E10)),INT($J$1-VALUE(LEFT(E10,FIND(" ",E10)-1))/24),IF(ISNUMBER(SEARCH("day",E10)),$J$1-VALUE(LEFT(E10,FIND(" ",E10)-1)),DATE(2000+VALUE(RIGHT(E10,2)),MATCH(MID(E10,FIND("-",E10)+1,3),{"Jan","Feb","Mar","Apr","May","Jun","Jul","Aug","Sep","Oct","Nov","Dec"},0),VALUE(LEFT(E10,FIND("-",E10)-1))))) -> 46293 | K10: =YEAR(J10)*100+MONTH(J10) -> 202609 | L10: =IF(OR(ISNUMBER(SEARCH("stock",C10)),ISNUMBER(SEARCH("forecast",C10)),ISNUMBER(SEARCH("earnings",C10)),ISNUMBER(SEARCH("ipo ",C10&" ")),ISNUMBER(SEARCH("ipo,",C10)),ISNUMBER(SEARCH("lockup",C10)),ISNUMBER(SEARCH("price",C10)),ISNUMBER(SEARCH("mstr",C10)),ISNUMBER(SEARCH("tsm",C10)),ISNUMBER(SEARCH("nvda",C10)),ISNUMBER(SEARCH(" vs ",C10))),1,0) -> 0
A11: https://www.techi.com/cerebras-lockup-expiration-cbrs-share-supply/ | B11: AI | C11: Cerebras Lockup: 171M CBRS Shares Can Test a 34.5M IPO Float | D11: Umair Aslam | E11: 26-Sep-26 | F11: 11 | G11: analysis | H11: 1 | I11: 1 | J11: =IF(ISNUMBER(SEARCH("hour",E11)),INT($J$1-VALUE(LEFT(E11,FIND(" ",E11)-1))/24),IF(ISNUMBER(SEARCH("day",E11)),$J$1-VALUE(LEFT(E11,FIND(" ",E11)-1)),DATE(2000+VALUE(RIGHT(E11,2)),MATCH(MID(E11,FIND("-",E11)+1,3),{"Jan","Feb","Mar","Apr","May","Jun","Jul","Aug","Sep","Oct","Nov","Dec"},0),VALUE(LEFT(E11,FIND("-",E11)-1))))) -> 46291 | K11: =YEAR(J11)*100+MONTH(J11) -> 202609 | L11: =IF(OR(ISNUMBER(SEARCH("stock",C11)),ISNUMBER(SEARCH("forecast",C11)),ISNUMBER(SEARCH("earnings",C11)),ISNUMBER(SEARCH("ipo ",C11&" ")),ISNUMBER(SEARCH("ipo,",C11)),ISNUMBER(SEARCH("lockup",C11)),ISNUMBER(SEARCH("price",C11)),ISNUMBER(SEARCH("mstr",C11)),ISNUMBER(SEARCH("tsm",C11)),ISNUMBER(SEARCH("nvda",C11)),ISNUMBER(SEARCH(" vs ",C11))),1,0) -> 1
A12: https://www.techi.com/akamai-anthropic-deal-capex-warrant-dilution/ | B12: AI | C12: Akamai’s $11.6B Anthropic Deal Comes With $5.5B Capex | D12: Umair Aslam | E12: 25-Sep-26 | F12: 8 | G12: analysis | H12: 1 | I12: 1 | J12: =IF(ISNUMBER(SEARCH("hour",E12)),INT($J$1-VALUE(LEFT(E12,FIND(" ",E12)-1))/24),IF(ISNUMBER(SEARCH("day",E12)),$J$1-VALUE(LEFT(E12,FIND(" ",E12)-1)),DATE(2000+VALUE(RIGHT(E12,2)),MATCH(MID(E12,FIND("-",E12)+1,3),{"Jan","Feb","Mar","Apr","May","Jun","Jul","Aug","Sep","Oct","Nov","Dec"},0),VALUE(LEFT(E12,FIND("-",E12)-1))))) -> 46290 | K12: =YEAR(J12)*100+MONTH(J12) -> 202609 | L12: =IF(OR(ISNUMBER(SEARCH("stock",C12)),ISNUMBER(SEARCH("forecast",C12)),ISNUMBER(SEARCH("earnings",C12)),ISNUMBER(SEARCH("ipo ",C12&" ")),ISNUMBER(SEARCH("ipo,",C12)),ISNUMBER(SEARCH("lockup",C12)),ISNUMBER(SEARCH("price",C12)),ISNUMBER(SEARCH("mstr",C12)),ISNUMBER(SEARCH("tsm",C12)),ISNUMBER(SEARCH("nvda",C12)),ISNUMBER(SEARCH(" vs ",C12))),1,0) -> 0
A13: https://www.techi.com/nvidia-vs-palantir-stock-better-buy-now/ | B13: AI | C13: Nvidia vs Palantir Stock: Which Is the Better Buy Now? | D13: Umair Aslam | E13: 25-Sep-26 | F13: 10 | G13: analysis | H13: 1 | I13: 0 | J13: =IF(ISNUMBER(SEARCH("hour",E13)),INT($J$1-VALUE(LEFT(E13,FIND(" ",E13)-1))/24),IF(ISNUMBER(SEARCH("day",E13)),$J$1-VALUE(LEFT(E13,FIND(" ",E13)-1)),DATE(2000+VALUE(RIGHT(E13,2)),MATCH(MID(E13,FIND("-",E13)+1,3),{"Jan","Feb","Mar","Apr","May","Jun","Jul","Aug","Sep","Oct","Nov","Dec"},0),VALUE(LEFT(E13,FIND("-",E13)-1))))) -> 46290 | K13: =YEAR(J13)*100+MONTH(J13) -> 202609 | L13: =IF(OR(ISNUMBER(SEARCH("stock",C13)),ISNUMBER(SEARCH("forecast",C13)),ISNUMBER(SEARCH("earnings",C13)),ISNUMBER(SEARCH("ipo ",C13&" ")),ISNUMBER(SEARCH("ipo,",C13)),ISNUMBER(SEARCH("lockup",C13)),ISNUMBER(SEARCH("price",C13)),ISNUMBER(SEARCH("mstr",C13)),ISNUMBER(SEARCH("tsm",C13)),ISNUMBER(SEARCH("nvda",C13)),ISNUMBER(SEARCH(" vs ",C13))),1,0) -> 1
A14: https://www.techi.com/microsoft-copilot-home-code-autopilot-billing/ | B14: AI | C14: Microsoft Copilot Rebuild Adds Home, Code and Autopilot | D14: Saba Javed | E14: 25-Sep-26 | F14: 8 | G14: news | H14: 1 | I14: 0 | J14: =IF(ISNUMBER(SEARCH("hour",E14)),INT($J$1-VALUE(LEFT(E14,FIND(" ",E14)-1))/24),IF(ISNUMBER(SEARCH("day",E14)),$J$1-VALUE(LEFT(E14,FIND(" ",E14)-1)),DATE(2000+VALUE(RIGHT(E14,2)),MATCH(MID(E14,FIND("-",E14)+1,3),{"Jan","Feb","Mar","Apr","May","Jun","Jul","Aug","Sep","Oct","Nov","Dec"},0),VALUE(LEFT(E14,FIND("-",E14)-1))))) -> 46290 | K14: =YEAR(J14)*100+MONTH(J14) -> 202609 | L14: =IF(OR(ISNUMBER(SEARCH("stock",C14)),ISNUMBER(SEARCH("forecast",C14)),ISNUMBER(SEARCH("earnings",C14)),ISNUMBER(SEARCH("ipo ",C14&" ")),ISNUMBER(SEARCH("ipo,",C14)),ISNUMBER(SEARCH("lockup",C14)),ISNUMBER(SEARCH("price",C14)),ISNUMBER(SEARCH("mstr",C14)),ISNUMBER(SEARCH("tsm",C14)),ISNUMBER(SEARCH("nvda",C14)),ISNUMBER(SEARCH(" vs ",C14))),1,0) -> 0
A15: https://www.techi.com/meta-vs-alphabet-stock-connect-valuation/ | B15: AI | C15: Meta vs Alphabet Stock: 4.8-Point Split Before Connect | D15: Umair Aslam | E15: 23-Sep-26 | F15: 8 | G15: analysis | H15: 1 | I15: 1 | J15: =IF(ISNUMBER(SEARCH("hour",E15)),INT($J$1-VALUE(LEFT(E15,FIND(" ",E15)-1))/24),IF(ISNUMBER(SEARCH("day",E15)),$J$1-VALUE(LEFT(E15,FIND(" ",E15)-1)),DATE(2000+VALUE(RIGHT(E15,2)),MATCH(MID(E15,FIND("-",E15)+1,3),{"Jan","Feb","Mar","Apr","May","Jun","Jul","Aug","Sep","Oct","Nov","Dec"},0),VALUE(LEFT(E15,FIND("-",E15)-1))))) -> 46288 | K15: =YEAR(J15)*100+MONTH(J15) -> 202609 | L15: =IF(OR(ISNUMBER(SEARCH("stock",C15)),ISNUMBER(SEARCH("forecast",C15)),ISNUMBER(SEARCH("earnings",C15)),ISNUMBER(SEARCH("ipo ",C15&" ")),ISNUMBER(SEARCH("ipo,",C15)),ISNUMBER(SEARCH("lockup",C15)),ISNUMBER(SEARCH("price",C15)),ISNUMBER(SEARCH("mstr",C15)),ISNUMBER(SEARCH("tsm",C15)),ISNUMBER(SEARCH("nvda",C15)),ISNUMBER(SEARCH(" vs ",C15))),1,0) -> 1
... A123: https://www.techi.com/top-network-security-companies/ | B123: Guides | C123: Top 5 Network Security Companies Every Business Should Know | D123: Muhammad Saqib | E123: 11-Mar-26 | F123: 9 | G123: guide | H123: 0 | I123: 1 | J123: =IF(ISNUMBER(SEARCH("hour",E123)),INT($J$1-VALUE(LEFT(E123,FIND(" ",E123)-1))/24),IF(ISNUMBER(SEARCH("day",E123)),$J$1-VALUE(LEFT(E123,FIND(" ",E123)-1)),DATE(2000+VALUE(RIGHT(E123,2)),MATCH(MID(E123,FIND("-",E123)+1,3),{"Jan","Feb","Mar","Apr","May","Jun","Jul","Aug","Sep","Oct","Nov","Dec"},0),VALUE(LEFT(E123,FIND("-",E123)-1))))) -> 46092 | K123: =YEAR(J123)*100+MONTH(J123) -> 202603 | L123: =IF(OR(ISNUMBER(SEARCH("stock",C123)),ISNUMBER(SEARCH("forecast",C123)),ISNUMBER(SEARCH("earnings",C123)),ISNUMBER(SEARCH("ipo ",C123&" ")),ISNUMBER(SEARCH("ipo,",C123)),ISNUMBER(SEARCH("lockup",C123)),ISNUMBER(SEARCH("price",C123)),ISNUMBER(SEARCH("mstr",C123)),ISNUMBER(SEARCH("tsm",C123)),ISNUMBER(SEARCH("nvda",C123)),ISNUMBER(SEARCH(" vs ",C123))),1,0) -> 0

Sheet Windows
A1: Section | B1: Rows | C1: Oldest (of 20 newest) | D1: Newest | E1: Window (days before scrape) | F1: Days since newest | G1: Ticker-type headlines (of 20) | H1: Guides-style format ('guide') | I1: Unique to this section (not also in another)
A2: AI | B2: =COUNTIF(Articles!$B$4:$B$123,A2) -> 20 | C2: =_xlfn.MINIFS(Articles!$J$4:$J$123,Articles!$B$4:$B$123,A2) -> 46286 | D2: =_xlfn.MAXIFS(Articles!$J$4:$J$123,Articles!$B$4:$B$123,A2) -> 46297 | E2: =Articles!$J$1-C2 -> 12 | F2: =Articles!$J$1-D2 -> 1 | G2: =SUMIFS(Articles!$L$4:$L$123,Articles!$B$4:$B$123,A2) -> 10 | H2: =COUNTIFS(Articles!$B$4:$B$123,A2,Articles!$G$4:$G$123,"guide") -> 0 | I2: =SUMPRODUCT((Articles!$B$4:$B$123=A2)*(COUNTIF(Articles!$A$4:$A$123,Articles!$A$4:$A$123)=1)) -> 20
A3: Markets | B3: =COUNTIF(Articles!$B$4:$B$123,A3) -> 20 | C3: =_xlfn.MINIFS(Articles!$J$4:$J$123,Articles!$B$4:$B$123,A3) -> 46212 | D3: =_xlfn.MAXIFS(Articles!$J$4:$J$123,Articles!$B$4:$B$123,A3) -> 46297 | E3: =Articles!$J$1-C3 -> 86 | F3: =Articles!$J$1-D3 -> 1 | G3: =SUMIFS(Articles!$L$4:$L$123,Articles!$B$4:$B$123,A3) -> 10 | H3: =COUNTIFS(Articles!$B$4:$B$123,A3,Articles!$G$4:$G$123,"guide") -> 0 | I3: =SUMPRODUCT((Articles!$B$4:$B$123=A3)*(COUNTIF(Articles!$A$4:$A$123,Articles!$A$4:$A$123)=1)) -> 18
A4: Crypto | B4: =COUNTIF(Articles!$B$4:$B$123,A4) -> 20 | C4: =_xlfn.MINIFS(Articles!$J$4:$J$123,Articles!$B$4:$B$123,A4) -> 46130 | D4: =_xlfn.MAXIFS(Articles!$J$4:$J$123,Articles!$B$4:$B$123,A4) -> 46297 | E4: =Articles!$J$1-C4 -> 168 | F4: =Articles!$J$1-D4 -> 1 | G4: =SUMIFS(Articles!$L$4:$L$123,Articles!$B$4:$B$123,A4) -> 6 | H4: =COUNTIFS(Articles!$B$4:$B$123,A4,Articles!$G$4:$G$123,"guide") -> 1 | I4: =SUMPRODUCT((Articles!$B$4:$B$123=A4)*(COUNTIF(Articles!$A$4:$A$123,Articles!$A$4:$A$123)=1)) -> 18
A5: Breakthroughs | B5: =COUNTIF(Articles!$B$4:$B$123,A5) -> 20 | C5: =_xlfn.MINIFS(Articles!$J$4:$J$123,Articles!$B$4:$B$123,A5) -> 46218 | D5: =_xlfn.MAXIFS(Articles!$J$4:$J$123,Articles!$B$4:$B$123,A5) -> 46291 | E5: =Articles!$J$1-C5 -> 80 | F5: =Articles!$J$1-D5 -> 7 | G5: =SUMIFS(Articles!$L$4:$L$123,Articles!$B$4:$B$123,A5) -> 4 | H5: =COUNTIFS(Articles!$B$4:$B$123,A5,Articles!$G$4:$G$123,"guide") -> 0 | I5: =SUMPRODUCT((Articles!$B$4:$B$123=A5)*(COUNTIF(Articles!$A$4:$A$123,Articles!$A$4:$A$123)=1)) -> 20
A6: Policy | B6: =COUNTIF(Articles!$B$4:$B$123,A6) -> 20 | C6: =_xlfn.MINIFS(Articles!$J$4:$J$123,Articles!$B$4:$B$123,A6) -> 46151 | D6: =_xlfn.MAXIFS(Articles!$J$4:$J$123,Articles!$B$4:$B$123,A6) -> 46253 | E6: =Articles!$J$1-C6 -> 147 | F6: =Articles!$J$1-D6 -> 45 | G6: =SUMIFS(Articles!$L$4:$L$123,Articles!$B$4:$B$123,A6) -> 1 | H6: =COUNTIFS(Articles!$B$4:$B$123,A6,Articles!$G$4:$G$123,"guide") -> 0 | I6: =SUMPRODUCT((Articles!$B$4:$B$123=A6)*(COUNTIF(Articles!$A$4:$A$123,Articles!$A$4:$A$123)=1)) -> 19
A7: Guides | B7: =COUNTIF(Articles!$B$4:$B$123,A7) -> 20 | C7: =_xlfn.MINIFS(Articles!$J$4:$J$123,Articles!$B$4:$B$123,A7) -> 46092 | D7: =_xlfn.MAXIFS(Articles!$J$4:$J$123,Articles!$B$4:$B$123,A7) -> 46243 | E7: =Articles!$J$1-C7 -> 206 | F7: =Articles!$J$1-D7 -> 55 | G7: =SUMIFS(Articles!$L$4:$L$123,Articles!$B$4:$B$123,A7) -> 1 | H7: =COUNTIFS(Articles!$B$4:$B$123,A7,Articles!$G$4:$G$123,"guide") -> 8 | I7: =SUMPRODUCT((Articles!$B$4:$B$123=A7)*(COUNTIF(Articles!$A$4:$A$123,Articles!$A$4:$A$123)=1)) -> 19
A9: Reading: the AI 20 newest cover 12 days, the Guides 20 cover 206. Section windows are not comparable. 3 URLs appear under two sections.

Sheet Guides
A1: month | B1: month_key | C1: Guides sessions (reported) | D1: Guides sessions (adjusted, central k) | E1: Articles listed in Guides | F1: Signups MoM change | G1: Site share (reported)
A2: 2026-03 | B2: 202603 | C2: =Traffic!G8 -> 4930 | D2: =C2/Step!$B$12 -> 3416.9219 | E2: =COUNTIFS(Articles!$B$4:$B$123,"Guides",Articles!$K$4:$K$123,B2) -> 3 | F2: =Traffic!H8-Traffic!H7 -> 30 | G2: =C2/Traffic!J8 -> 0.051051051
A3: 2026-04 | B3: 202604 | C3: =Traffic!G9 -> 2175 | D3: =C3/Step!$B$12 -> 1507.4655 | E3: =COUNTIFS(Articles!$B$4:$B$123,"Guides",Articles!$K$4:$K$123,B3) -> 0 | F3: =Traffic!H9-Traffic!H8 -> 30 | G3: =C3/Traffic!J9 -> 0.02269289
A4: 2026-05 | B4: 202605 | C4: =Traffic!G10 -> 1595 | D4: =C4/Step!$B$12 -> 1105.4747 | E4: =COUNTIFS(Articles!$B$4:$B$123,"Guides",Articles!$K$4:$K$123,B4) -> 3 | F4: =Traffic!H10-Traffic!H9 -> 30 | G4: =C4/Traffic!J10 -> 0.016369048
A5: 2026-06 | B5: 202606 | C5: =Traffic!G11 -> 1160 | D5: =C5/Step!$B$12 -> 803.98162 | E5: =COUNTIFS(Articles!$B$4:$B$123,"Guides",Articles!$K$4:$K$123,B5) -> 2 | F5: =Traffic!H11-Traffic!H10 -> 30 | G5: =C5/Traffic!J11 -> 0.011713031
A6: 2026-07 | B6: 202607 | C6: =Traffic!G12 -> 870 | D6: =C6/Step!$B$12 -> 602.98622 | E6: =COUNTIFS(Articles!$B$4:$B$123,"Guides",Articles!$K$4:$K$123,B6) -> 11 | F6: =Traffic!H12-Traffic!H11 -> 30 | G6: =C6/Traffic!J12 -> 0.0086206897
A7: 2026-08 | B7: 202608 | C7: =Traffic!G13 -> 725 | D7: =C7/Step!$B$12 -> 502.48851 | E7: =COUNTIFS(Articles!$B$4:$B$123,"Guides",Articles!$K$4:$K$123,B7) -> 1 | F7: =Traffic!H13-Traffic!H12 -> 40 | G7: =C7/Traffic!J13 -> 0.0070521862
A9: Mar counts 11-31 Mar only (oldest Guides row is 11 Mar). Apr-Aug complete. Note Apr: sessions -2,755 while signup gain stayed +30 (on trend).
A10: Guides adjusted, Mar -> Aug | D10: =D7/D2-1 -> -0.85294118
A11: Guides share of reported sessions: Sep-25 / Aug-26 | C11: =Traffic!G2/Traffic!J2 -> 0.071304348 | D11: =Traffic!G13/Traffic!J13 -> 0.0070521862

Sheet Checks
A1: Check | B1: Result | C1: Expected
A2: Rows in Articles | B2: =COUNTA(Articles!A4:A123) -> 120 | C2: 120 | D2: =IF(ROUND(B2,3)=C2,"OK","CHECK") -> OK
A3: Blank cells in 9 columns | B3: =COUNTBLANK(Articles!A4:I123) -> 0 | C3: 0 | D3: =IF(ROUND(B3,3)=C3,"OK","CHECK") -> OK
A4: Headline word count != column F (recomputed) | B4: =SUMPRODUCT(--((LEN(TRIM(Articles!C4:C123))-LEN(SUBSTITUTE(TRIM(Articles!C4:C123)," ",""))+1)<>Articles!F4:F123)) -> 0 | C4: 0 | D4: =IF(ROUND(B4,3)=C4,"OK","CHECK") -> OK
A5: contains_a_number != any digit in headline | B5: =SUMPRODUCT(--((((ISNUMBER(SEARCH("0",Articles!C4:C123))+ISNUMBER(SEARCH("1",Articles!C4:C123))+ISNUMBER(SEARCH("2",Articles!C4:C123))+ISNUMBER(SEARCH("3",Articles!C4:C123))+ISNUMBER(SEARCH("4",Articles!C4:C123))+ISNUMBER(SEARCH("5",Articles!C4:C123))+ISNUMBER(SEARCH("6",Articles!C4:C123))+ISNUMBER(SEARCH("7",Articles!C4:C123))+ISNUMBER(SEARCH("8",Articles!C4:C123))+ISNUMBER(SEARCH("9",Articles!C4:C123)))>0)*1)<>Articles!I4:I123)) -> 0 | C5: 0 | D5: =IF(ROUND(B5,3)=C5,"OK","CHECK") -> OK
A6: Duplicate URLs (cross-listed articles) | B6: =SUMPRODUCT(--(COUNTIF(Articles!A4:A123,Articles!A4:A123)>1)) -> 6 | C6: 6 | D6: =IF(ROUND(B6,3)=C6,"OK","CHECK") -> OK
A7: Unique URLs | B7: =SUMPRODUCT(1/COUNTIF(Articles!A4:A123,Articles!A4:A123)) -> 117 | C7: 117 | D7: =IF(ROUND(B7,3)=C7,"OK","CHECK") -> OK
A8: Reported Aug/Sep ratio check vs analysis.py (0.788) | B8: =ROUND(Underlying!B15,3) -> 0.788 | C8: 0.788 | D8: =IF(ROUND(B8,3)=C8,"OK","CHECK") -> OK
A9: Underlying central vs analysis.py (0.239) | B9: =ROUND(Underlying!B16,3) -> 0.239 | C9: 0.239 | D9: =IF(ROUND(B9,3)=C9,"OK","CHECK") -> OK
